AgamPrimer/AgamPrimer.py
AgamPrimer/__init__.py
agamprimer-0.6.9.dist-info/LICENSE
agamprimer-0.6.9.dist-info/METADATA
agamprimer-0.6.9.dist-info/WHEEL
agamprimer-0.6.9.dist-info/RECORD
